imagequant/libimagequant_build.py
imagequant/__init__.py
imagequant/_libimagequant.abi3.so
imagequant-1.1.4.dist-info/RECORD
imagequant-1.1.4.dist-info/LICENSE
imagequant-1.1.4.dist-info/WHEEL
imagequant-1.1.4.dist-info/top_level.txt
imagequant-1.1.4.dist-info/METADATA
