Metadata-Version: 2.1
Name: imagequant
Version: 1.1.4
Summary: Image Quantization Library
Home-page: https://github.com/wanadev/imagequant-python
Author: Wanadev
Author-email: contact@wanadev.fr
Maintainer: Fabien LOISON
License: BSD-3-Clause
Project-URL: Source Code, https://github.com/wanadev/imagequant-python
Project-URL: Documentation, https://github.com/wanadev/imagequant-python#usage
Project-URL: Changelog, https://github.com/wanadev/imagequant-python#changelog
Project-URL: Issues, https://github.com/wanadev/imagequant-python/issues
Project-URL: Chat, https://discord.gg/BmUkEdMuFp
Keywords: image libimagequant pngquant cffi
License-File: LICENSE
Requires-Dist: cffi >=1.0.0
Provides-Extra: dev
Requires-Dist: nox ; extra == 'dev'
Requires-Dist: flake8 ; extra == 'dev'
Requires-Dist: black ; extra == 'dev'
Requires-Dist: pytest ; extra == 'dev'
Provides-Extra: pil
Requires-Dist: pillow ; extra == 'pil'
